{
  "name": "qa-dec",
  "json_class": "Chef::Environment",
  "chef_type": "environment",
  "description": "QA environment specfication file for Data extraction and correction",

  "cookbook_versions": {

  },

  "default_attributes": {
    "aws_account_id":"716533421362",
    "aws_region":"us-east-1",
    "logstash": {
      "server_name": "qa-logstash01.aws.phenom.local",
      "server_port": "5004",
      "certificate_name": "qacert"
    },
    "elasticsearch": {
      "elb_hostname": "qa-elasticsearch-elb.aws.phenom.local",
      "elb_port"    : 9200
    },
    "kafka":{
      "cluster": ["qa-kafka01", "qa-kafka02", "qa-kafka03"]
    },
    "zookeeper":{
      "cluster": ["qa-kafka01", "qa-kafka02", "qa-kafka03"]
    }
  },
  "override_attributes": {
    "kafka-logs-backup": {
      "config_repo": {
        "branch": "QA"
      }
    }
  }
}
